sqlmake/__init__.py
sqlmake/__main__.py
sqlmake/fileparser.py
sqlmake/indexer.py
SqlMake-0.3.0.dist-info/LICENSE
SqlMake-0.3.0.dist-info/METADATA
SqlMake-0.3.0.dist-info/WHEEL
SqlMake-0.3.0.dist-info/entry_points.txt
SqlMake-0.3.0.dist-info/top_level.txt
SqlMake-0.3.0.dist-info/RECORD
