Metadata-Version: 2.1
Name: SqlMake
Version: 0.3.0
Summary: Command line tool to build a SQL schema
Home-page: https://github.com/amvtek/SqlMake/
Author: AmvTek developers
Author-email: devel@amvtek.com
License: MIT
Project-URL: Documentation, https://sqlmake.readthedocs.org/en/latest/
Project-URL: Source, https://github.com/amvtek/SqlMake/
Project-URL: Tracker, https://github.com/amvtek/SqlMake/issues
Project-URL: Download, https://pypi.org/project/SqlMake/#files
Platform: UNKNOWN
Classifier: Development Status :: 3 - Alpha
Classifier: Topic :: Utilities
Classifier: Programming Language :: Python
Classifier: Programming Language :: Python :: 3
Classifier: Programming Language :: Python :: 3 :: Only
Classifier: Environment :: Console
Classifier: Intended Audience :: Developers
Classifier: License :: OSI Approved :: MIT License
Classifier: Operating System :: POSIX :: Linux
Classifier: Operating System :: Unix
Classifier: Operating System :: MacOS
Classifier: Operating System :: Microsoft :: Windows
Requires-Python: >=3.6
License-File: LICENSE
Requires-Dist: toposort (~=1.7)
Requires-Dist: Jinja2 (~=3.0.3)
